<archimate:ArchimateDiagramModel
    xmlns:xsi="http://www.w3.org/2001/XMLSchema-instance"
    xmlns:archimate="http://www.archimatetool.com/archimate"
    name="Domener"
    id="326f6a8b-883a-4461-9e51-0b9f5b7e559b">
  <children
      xsi:type="archimate:DiagramModelGroup"
      id="39a11cc5-22ab-4939-9f63-b0e1242e4449"
      name="Insentiv"
      fontColor="#ffffff"
      textAlignment="1"
      fillColor="#8080c0">
    <bounds
        x="39"
        y="110"
        width="778"
        height="140"/>
    <children
        xsi:type="archimate:DiagramModelReference"
        id="c558f2d2-4e8e-4b3c-b77a-8f07e75abdb8">
      <bounds
          x="36"
          y="48"
          width="120"
          height="55"/>
      <referencedModel
          xsi:type="archimate:ArchimateDiagramModel"
          href="ArchimateDiagramModel_6f9afe44-bc5e-4959-8aca-3c06e944a373.xml#6f9afe44-bc5e-4959-8aca-3c06e944a373"/>
    </children>
    <children
        xsi:type="archimate:DiagramModelReference"
        id="bd9e594b-8d78-4d49-9b6b-844eb368097f">
      <bounds
          x="192"
          y="48"
          width="120"
          height="55"/>
      <referencedModel
          xsi:type="archimate:ArchimateDiagramModel"
          href="ArchimateDiagramModel_e934adbf-8828-45dd-81e6-81607450bb23.xml#e934adbf-8828-45dd-81e6-81607450bb23"/>
    </children>
  </children>
  <children
      xsi:type="archimate:DiagramModelGroup"
      id="dd907461-9552-4ef6-b501-b063c803bdf6"
      name="Strategi"
      fontColor="#ffffff"
      textAlignment="1"
      fillColor="#804040">
    <bounds
        x="39"
        y="288"
        width="778"
        height="140"/>
    <children
        xsi:type="archimate:DiagramModelReference"
        id="d0fe826c-3ae5-4a64-bebc-22f197c0e093">
      <bounds
          x="36"
          y="48"
          width="120"
          height="55"/>
      <referencedModel
          xsi:type="archimate:ArchimateDiagramModel"
          href="ArchimateDiagramModel_42d1b9fe-8960-41ff-b2cb-678de8a9ec6d.xml#42d1b9fe-8960-41ff-b2cb-678de8a9ec6d"/>
    </children>
    <children
        xsi:type="archimate:DiagramModelReference"
        id="5d35e876-3e51-46f2-b5dd-14dca63ab3bf">
      <bounds
          x="192"
          y="48"
          width="120"
          height="55"/>
      <referencedModel
          xsi:type="archimate:ArchimateDiagramModel"
          href="ArchimateDiagramModel_dfd49927-c01a-4890-81be-7f9a23e39893.xml#dfd49927-c01a-4890-81be-7f9a23e39893"/>
    </children>
    <children
        xsi:type="archimate:DiagramModelReference"
        id="90bfd5d6-8ce9-446f-912c-a5c7ee8bf685">
      <bounds
          x="348"
          y="48"
          width="120"
          height="55"/>
      <referencedModel
          xsi:type="archimate:ArchimateDiagramModel"
          href="ArchimateDiagramModel_4e62a2cc-9578-4ce4-b3f8-6d367f389e29.xml#4e62a2cc-9578-4ce4-b3f8-6d367f389e29"/>
    </children>
    <children
        xsi:type="archimate:DiagramModelReference"
        id="c1e7ada5-9c17-4868-87cf-6dfdeb4afeb6">
      <bounds
          x="504"
          y="48"
          width="120"
          height="55"/>
      <referencedModel
          xsi:type="archimate:ArchimateDiagramModel"
          href="ArchimateDiagramModel_c1efaf8c-0f24-4579-99f0-670318ef8fe7.xml#c1efaf8c-0f24-4579-99f0-670318ef8fe7"/>
    </children>
  </children>
  <children
      xsi:type="archimate:DiagramModelGroup"
      id="b76d5de0-6af6-4870-9829-fcbf569b9e2e"
      name="Forretning"
      textAlignment="1"
      fillColor="#ffff00">
    <bounds
        x="39"
        y="468"
        width="778"
        height="140"/>
    <children
        xsi:type="archimate:DiagramModelReference"
        id="5804b36b-0dee-443b-92a9-b851953418b1">
      <bounds
          x="324"
          y="48"
          width="120"
          height="55"/>
      <referencedModel
          xsi:type="archimate:ArchimateDiagramModel"
          href="ArchimateDiagramModel_b93a4586-3f7a-421b-b3ea-8dce61a6ca71.xml#b93a4586-3f7a-421b-b3ea-8dce61a6ca71"/>
    </children>
    <children
        xsi:type="archimate:DiagramModelReference"
        id="86fd8b4f-7893-4572-8d49-654330036b43">
      <bounds
          x="480"
          y="48"
          width="120"
          height="55"/>
      <referencedModel
          xsi:type="archimate:ArchimateDiagramModel"
          href="ArchimateDiagramModel_7640ee46-81f7-485a-bfab-0feaeed327ed.xml#7640ee46-81f7-485a-bfab-0feaeed327ed"/>
    </children>
    <children
        xsi:type="archimate:DiagramModelReference"
        id="e96c012f-2fa4-4940-8d99-1f5fb5b88f29">
      <bounds
          x="36"
          y="48"
          width="120"
          height="55"/>
      <referencedModel
          xsi:type="archimate:ArchimateDiagramModel"
          href="ArchimateDiagramModel_2acbe3c5-b6db-4abd-a8c2-83f3553149c2.xml#2acbe3c5-b6db-4abd-a8c2-83f3553149c2"/>
    </children>
  </children>
  <children
      xsi:type="archimate:DiagramModelGroup"
      id="d737eaa0-ad4c-412e-824e-69c925dfb6f5"
      name="Applikasjon"
      textAlignment="1"
      fillColor="#00ffff">
    <bounds
        x="39"
        y="648"
        width="502"
        height="140"/>
    <children
        xsi:type="archimate:DiagramModelReference"
        id="09ee4d7d-0619-4640-9b5e-a2038aea8791">
      <bounds
          x="36"
          y="48"
          width="120"
          height="55"/>
      <referencedModel
          xsi:type="archimate:ArchimateDiagramModel"
          href="ArchimateDiagramModel_822739b6-b365-47c6-8d4c-61683c0898c1.xml#822739b6-b365-47c6-8d4c-61683c0898c1"/>
    </children>
  </children>
  <children
      xsi:type="archimate:DiagramModelGroup"
      id="eea34efb-9bfa-4000-b3af-84e7ec09d133"
      name="Teknologi"
      textAlignment="1"
      fillColor="#00ff40">
    <bounds
        x="39"
        y="828"
        width="502"
        height="140"/>
  </children>
  <children
      xsi:type="archimate:DiagramModelGroup"
      id="32e130da-4167-495a-916a-558887e7f0fe"
      name="Implementering og overgang"
      textAlignment="1"
      fillColor="#ff80ff">
    <bounds
        x="39"
        y="1008"
        width="502"
        height="140"/>
  </children>
</archimate:ArchimateDiagramModel>
