<archimate:SketchModel
    xmlns:xsi="http://www.w3.org/2001/XMLSchema-instance"
    xmlns:archimate="http://www.archimatetool.com/archimate"
    name="New Sketch"
    id="id-9d963e46c5e94f55bbe42d98445a05d2">
  <children
      xsi:type="archimate:SketchModelSticky"
      id="id-e89556e32ea64ca4a739c53cb2fd83b1"
      name="Sticky"
      lineColor="#5c5c5c"
      textAlignment="1"
      fillColor="#ffffb5"
      content="Foretaksstyring">
    <bounds
        x="12"
        y="12"
        width="937"
        height="1105"/>
    <children
        xsi:type="archimate:SketchModelActor"
        id="id-26d8d53cae424fb1975c4583b3e82a2e"
        name="Administrerende direktlør">
      <bounds
          x="24"
          y="60"
          width="75"
          height="100"/>
    </children>
    <children
        xsi:type="archimate:SketchModelSticky"
        id="id-f7af198d3c0848138c89e3d60eb4d5a2"
        name="Sticky"
        lineColor="#5c5c5c"
        textAlignment="1"
        fillColor="#ffffb5"
        content="Avdeling&#xD;&#xA;Administrasjon">
      <bounds
          x="24"
          y="216"
          width="349"
          height="301"/>
      <children
          xsi:type="archimate:SketchModelSticky"
          id="id-b5fd1d1143b34dc39c2a6cbb59770ffa"
          name="Sticky"
          lineColor="#5c5c5c"
          textAlignment="1"
          fillColor="#ffffb5"
          content="Seksjon &#xD;&#xA;Kommunikasjon">
        <bounds
            y="108"
            width="135"
            height="49"/>
      </children>
      <children
          xsi:type="archimate:SketchModelSticky"
          id="id-88629da39dd14a7b8abd0e6c5321e678"
          name="Sticky"
          lineColor="#5c5c5c"
          textAlignment="1"
          fillColor="#ffffb5"
          content="Seksjon &#xD;&#xA;Økonomi">
        <bounds
            y="48"
            width="135"
            height="49"/>
      </children>
      <children
          xsi:type="archimate:SketchModelSticky"
          id="id-c0167fa79f7c48a7abbcb596e0040770"
          name="Sticky"
          lineColor="#5c5c5c"
          textAlignment="1"
          fillColor="#ffffb5"
          content="Seksjon &#xD;&#xA;HR">
        <bounds
            y="168"
            width="135"
            height="49"/>
      </children>
      <children
          xsi:type="archimate:SketchModelActor"
          id="id-f140150a5e024430be33a33836a584ea"
          name="Direktør Administrasjon">
        <bounds
            x="264"
            y="21"
            width="75"
            height="100"/>
      </children>
      <children
          xsi:type="archimate:SketchModelSticky"
          id="id-9e4b387381844133a543e30b6925518d"
          name="Sticky"
          lineColor="#5c5c5c"
          textAlignment="1"
          fillColor="#ffffb5"
          content="Seksjon Virksomhetsstyring">
        <bounds
            y="228"
            width="135"
            height="49"/>
      </children>
    </children>
    <children
        xsi:type="archimate:SketchModelSticky"
        id="id-0a904a53e4104f79bae0484451c28578"
        name="Sticky"
        lineColor="#5c5c5c"
        textAlignment="1"
        fillColor="#ffffb5"
        content="Divisjon STA og BHM">
      <bounds
          x="432"
          y="216"
          width="289"
          height="697"/>
      <children
          xsi:type="archimate:SketchModelSticky"
          id="id-96d51f76731c43dd8ddc99993c22d5b1"
          name="Sticky"
          lineColor="#5c5c5c"
          textAlignment="1"
          fillColor="#ffffb5"
          content="Avdeling &#xD;&#xA;Anskaffelse">
        <bounds
            x="12"
            y="132"
            width="135"
            height="409"/>
      </children>
      <children
          xsi:type="archimate:SketchModelSticky"
          id="id-b5044c0992a349f3be0bff53aa20b8f7"
          name="Sticky"
          lineColor="#5c5c5c"
          textAlignment="1"
          fillColor="#ffffb5"
          content="Avdeling Avtaleforvaltning">
        <bounds
            x="12"
            y="60"
            width="135"
            height="61"/>
      </children>
      <children
          xsi:type="archimate:SketchModelActor"
          id="id-982dcd9a13a943b088c91c7f3f65a899"
          name="Direktør STA og BHM">
        <bounds
            x="192"
            y="60"
            width="75"
            height="100"/>
      </children>
    </children>
    <children
        xsi:type="archimate:SketchModelSticky"
        id="id-23289c0a56474fcba09f233d3d60492f"
        name="Sticky"
        lineColor="#5c5c5c"
        textAlignment="1"
        fillColor="#ffffb5"
        content="Avdeling &#xD;&#xA;Digitalisering">
      <bounds
          x="24"
          y="576"
          width="349"
          height="337"/>
      <children
          xsi:type="archimate:SketchModelSticky"
          id="id-75649baa367c46d6a283dadb704d262f"
          name="Sticky"
          lineColor="#5c5c5c"
          textAlignment="1"
          fillColor="#ffffb5"
          content="Seksjon&#xD;&#xA;IKT">
        <bounds
            y="60"
            width="135"
            height="253"/>
        <children
            xsi:type="archimate:SketchModelSticky"
            id="id-b57ae263e6a3424e884fdf96618cde2e"
            name="Sticky"
            lineColor="#5c5c5c"
            textAlignment="1"
            fillColor="#ffffb5"
            content="Enhet fagsystem">
          <bounds
              y="144"
              width="135"
              height="39"/>
        </children>
        <children
            xsi:type="archimate:SketchModelSticky"
            id="id-654cb2b14ac34865b33ac392841e50b4"
            name="Sticky"
            lineColor="#5c5c5c"
            textAlignment="1"
            fillColor="#ffffb5"
            content="Enhet brukerstøtte">
          <bounds
              y="48"
              width="135"
              height="39"/>
        </children>
        <children
            xsi:type="archimate:SketchModelSticky"
            id="id-48ab525243ef48b99d12c1820cdfc53e"
            name="Sticky"
            lineColor="#5c5c5c"
            textAlignment="1"
            fillColor="#ffffb5"
            content="Enhet dokumentasjonsforvalting">
          <bounds
              y="192"
              width="135"
              height="39"/>
        </children>
        <children
            xsi:type="archimate:SketchModelSticky"
            id="id-1df7f93936a74ba39ade219931855e84"
            name="Sticky"
            lineColor="#5c5c5c"
            textAlignment="1"
            fillColor="#ffffb5"
            content="Enhet kontorstøtte">
          <bounds
              y="96"
              width="135"
              height="39"/>
        </children>
      </children>
      <children
          xsi:type="archimate:SketchModelSticky"
          id="id-7410132b949544fba2af3c8e353a03e2"
          name="Sticky"
          lineColor="#5c5c5c"
          textAlignment="1"
          fillColor="#ffffb5"
          content="Seksjon&#xD;&#xA;Analyse">
        <bounds
            x="204"
            y="156"
            width="135"
            height="157"/>
        <children
            xsi:type="archimate:SketchModelSticky"
            id="id-4922cd26cb5e4f69aa1a388050b8ac93"
            name="Sticky"
            lineColor="#5c5c5c"
            textAlignment="1"
            fillColor="#ffffb5"
            content="Enhet foretaksrapportering">
          <bounds
              y="48"
              width="135"
              height="39"/>
        </children>
        <children
            xsi:type="archimate:SketchModelSticky"
            id="id-7af5f835646c44129fe312f4fe6eb9a1"
            name="Sticky"
            lineColor="#5c5c5c"
            textAlignment="1"
            fillColor="#ffffb5"
            content="Enhet forbruksanalyse">
          <bounds
              y="96"
              width="135"
              height="39"/>
        </children>
      </children>
      <children
          xsi:type="archimate:SketchModelActor"
          id="id-f94456e7f2144fab93f8ced2a0da2807"
          name="Digitalisering, IKT og analyse">
        <bounds
            x="264"
            y="9"
            width="75"
            height="100"/>
      </children>
    </children>
    <children
        xsi:type="archimate:SketchModelSticky"
        id="id-24ac01eca18c4763aa2b8fb61648825d"
        name="Sticky"
        lineColor="#5c5c5c"
        textAlignment="1"
        fillColor="#ffffb5"
        content="Seksjon vest">
      <bounds
          x="756"
          y="504"
          width="135"
          height="70"/>
    </children>
    <children
        xsi:type="archimate:SketchModelSticky"
        id="id-0c7a3f89895f470e8e798d0b998f1e31"
        name="Sticky"
        lineColor="#5c5c5c"
        textAlignment="1"
        fillColor="#ffffb5"
        content="Seksjon nord">
      <bounds
          x="756"
          y="420"
          width="135"
          height="70"/>
    </children>
    <children
        xsi:type="archimate:SketchModelSticky"
        id="id-53c1c04dd2154310a231699d0e86242c"
        name="Sticky"
        lineColor="#5c5c5c"
        textAlignment="1"
        fillColor="#ffffb5"
        content="Seksjon Midt-Norge">
      <bounds
          x="756"
          y="588"
          width="135"
          height="70"/>
    </children>
    <children
        xsi:type="archimate:SketchModelSticky"
        id="id-f4568920e5054924b5f7b4a45e66c77c"
        name="Sticky"
        lineColor="#5c5c5c"
        textAlignment="1"
        fillColor="#ffffb5"
        content="Seksjon sør-øst">
      <bounds
          x="756"
          y="672"
          width="135"
          height="70"/>
    </children>
  </children>
  <children
      xsi:type="archimate:SketchModelSticky"
      id="id-a5ced6008ee14b04af5e9a1206601f11"
      name="Sticky"
      lineColor="#5c5c5c"
      textAlignment="1"
      fillColor="#ffffb5"
      content="Foretaksledelse">
    <bounds
        x="1020"
        y="12"
        width="937"
        height="1105"/>
    <children
        xsi:type="archimate:SketchModelActor"
        id="id-bf5cc6f0fcd44426921da27307eec10a"
        name="Administrerende direktlør">
      <bounds
          x="204"
          y="60"
          width="75"
          height="100"/>
    </children>
    <children
        xsi:type="archimate:SketchModelSticky"
        id="id-c145c61408a041f1bb2bbc6284930608"
        name="Sticky"
        lineColor="#5c5c5c"
        textAlignment="1"
        fillColor="#ffffb5"
        content="Divisjon&#xD;&#xA;Foretaksstyring">
      <bounds
          x="204"
          y="216"
          width="349"
          height="301"/>
      <children
          xsi:type="archimate:SketchModelSticky"
          id="id-8e98180100634eaca0396d1468ae1ad6"
          name="Sticky"
          lineColor="#5c5c5c"
          textAlignment="1"
          fillColor="#ffffb5"
          content="Avdeling&#xD;&#xA;Kommunikasjon">
        <bounds
            y="108"
            width="135"
            height="49"/>
      </children>
      <children
          xsi:type="archimate:SketchModelSticky"
          id="id-87ccc3226abf49a887e22bdf8ed81e20"
          name="Sticky"
          lineColor="#5c5c5c"
          textAlignment="1"
          fillColor="#ffffb5"
          content="Avdeling&#xD;&#xA;Økonomi">
        <bounds
            y="48"
            width="135"
            height="49"/>
      </children>
      <children
          xsi:type="archimate:SketchModelSticky"
          id="id-9f488b2b29d44c6aa03fb9105a8df39c"
          name="Sticky"
          lineColor="#5c5c5c"
          textAlignment="1"
          fillColor="#ffffb5"
          content="Avdeling&#xD;&#xA;HR">
        <bounds
            y="168"
            width="135"
            height="49"/>
      </children>
      <children
          xsi:type="archimate:SketchModelActor"
          id="id-2a667dbf8c65433781b2fd310f17cde4"
          name="Direktør Økonomi og virksomhetsstyring">
        <bounds
            x="264"
            y="21"
            width="75"
            height="100"/>
      </children>
      <children
          xsi:type="archimate:SketchModelSticky"
          id="id-7f39fa2169da40f2a08242db606e9840"
          name="Sticky"
          lineColor="#5c5c5c"
          textAlignment="1"
          fillColor="#ffffb5"
          content="Avdeling&#xD;&#xA;Styre og eieroppfølging">
        <bounds
            y="228"
            width="135"
            height="49"/>
      </children>
    </children>
    <children
        xsi:type="archimate:SketchModelSticky"
        id="id-db53befbd95249c4b1133ec3519bcbad"
        name="Sticky"
        lineColor="#5c5c5c"
        textAlignment="1"
        fillColor="#ffffb5"
        content="Divisjon STA og BHM">
      <bounds
          x="612"
          y="216"
          width="289"
          height="697"/>
      <children
          xsi:type="archimate:SketchModelSticky"
          id="id-39035d9ff27e48bca3da2b62dc3a861c"
          name="Sticky"
          lineColor="#5c5c5c"
          textAlignment="1"
          fillColor="#ffffb5"
          content="Avdeling &#xD;&#xA;Anskaffelse">
        <bounds
            x="12"
            y="132"
            width="135"
            height="409"/>
        <children
            xsi:type="archimate:SketchModelSticky"
            id="id-e2de0e39c3df40bd98fcb30358d5c6e2"
            name="Sticky"
            lineColor="#5c5c5c"
            textAlignment="1"
            fillColor="#ffffb5"
            content="Seksjon nord">
          <bounds
              y="60"
              width="135"
              height="70"/>
        </children>
        <children
            xsi:type="archimate:SketchModelSticky"
            id="id-b6ba57d71f8c4599b49ff357d079b87e"
            name="Sticky"
            lineColor="#5c5c5c"
            textAlignment="1"
            fillColor="#ffffb5"
            content="Seksjon vest">
          <bounds
              y="144"
              width="135"
              height="70"/>
        </children>
        <children
            xsi:type="archimate:SketchModelSticky"
            id="id-e67a4a553edf41938ddfb751ca5a8eea"
            name="Sticky"
            lineColor="#5c5c5c"
            textAlignment="1"
            fillColor="#ffffb5"
            content="Seksjon Midt-Norge">
          <bounds
              y="228"
              width="135"
              height="70"/>
        </children>
        <children
            xsi:type="archimate:SketchModelSticky"
            id="id-f62d1db4ff614a20b72a2e4af494f2f3"
            name="Sticky"
            lineColor="#5c5c5c"
            textAlignment="1"
            fillColor="#ffffb5"
            content="Seksjon sør-øst">
          <bounds
              y="312"
              width="135"
              height="70"/>
        </children>
      </children>
      <children
          xsi:type="archimate:SketchModelSticky"
          id="id-e24a944d12c54affb8bb4500255229d8"
          name="Sticky"
          lineColor="#5c5c5c"
          textAlignment="1"
          fillColor="#ffffb5"
          content="Avdeling Avtaleforvaltning">
        <bounds
            x="12"
            y="60"
            width="135"
            height="61"/>
      </children>
      <children
          xsi:type="archimate:SketchModelActor"
          id="id-13886e718b80439ba3238406c779bc83"
          name="Direktør STA og BHM">
        <bounds
            x="192"
            y="60"
            width="75"
            height="100"/>
      </children>
    </children>
    <children
        xsi:type="archimate:SketchModelSticky"
        id="id-e928b1db84274c8c9e2474a525c41442"
        name="Sticky"
        lineColor="#5c5c5c"
        textAlignment="1"
        fillColor="#ffffb5"
        content="Divisjon&#xD;&#xA;Digitalisering">
      <bounds
          x="204"
          y="576"
          width="349"
          height="337"/>
      <children
          xsi:type="archimate:SketchModelSticky"
          id="id-2b23bdafc71043a787fb3663c1406b6c"
          name="Sticky"
          lineColor="#5c5c5c"
          textAlignment="1"
          fillColor="#ffffb5"
          content="Avdeling&#xD;&#xA;IKT">
        <bounds
            y="60"
            width="135"
            height="253"/>
        <children
            xsi:type="archimate:SketchModelSticky"
            id="id-3bea91ff2415438894f9e446fb2ed08d"
            name="Sticky"
            lineColor="#5c5c5c"
            textAlignment="1"
            fillColor="#ffffb5"
            content="Seksjon &#xD;&#xA;fagsystem">
          <bounds
              y="144"
              width="135"
              height="39"/>
        </children>
        <children
            xsi:type="archimate:SketchModelSticky"
            id="id-0499c3c0f5e94c539ed4935c960e11a5"
            name="Sticky"
            lineColor="#5c5c5c"
            textAlignment="1"
            fillColor="#ffffb5"
            content="Seksjon brukerstøtte">
          <bounds
              y="48"
              width="135"
              height="39"/>
        </children>
        <children
            xsi:type="archimate:SketchModelSticky"
            id="id-36fbddc2648c41d39c1e892befda3997"
            name="Sticky"
            lineColor="#5c5c5c"
            textAlignment="1"
            fillColor="#ffffb5"
            content="Seksjon &#xD;&#xA;dokumentasjonsforvalting">
          <bounds
              y="192"
              width="135"
              height="39"/>
        </children>
        <children
            xsi:type="archimate:SketchModelSticky"
            id="id-60d326a8527845dab37f1e312442d07a"
            name="Sticky"
            lineColor="#5c5c5c"
            textAlignment="1"
            fillColor="#ffffb5"
            content="Seksjon kontorstøttesystem">
          <bounds
              y="96"
              width="135"
              height="39"/>
        </children>
      </children>
      <children
          xsi:type="archimate:SketchModelSticky"
          id="id-f8a5260974df4856ac273c9ccad4d85c"
          name="Sticky"
          lineColor="#5c5c5c"
          textAlignment="1"
          fillColor="#ffffb5"
          content="Avdeling&#xD;&#xA;Analyse">
        <bounds
            x="204"
            y="156"
            width="135"
            height="157"/>
        <children
            xsi:type="archimate:SketchModelSticky"
            id="id-86a562ee6d9e4a73bbd0db0c240777f5"
            name="Sticky"
            lineColor="#5c5c5c"
            textAlignment="1"
            fillColor="#ffffb5"
            content="Seksjon foretaksrapportering">
          <bounds
              y="48"
              width="135"
              height="39"/>
        </children>
        <children
            xsi:type="archimate:SketchModelSticky"
            id="id-0db952e9a81e497d9271f5e565c0b82c"
            name="Sticky"
            lineColor="#5c5c5c"
            textAlignment="1"
            fillColor="#ffffb5"
            content="Seksjon virksomhetsanalyse">
          <bounds
              y="96"
              width="135"
              height="39"/>
        </children>
      </children>
      <children
          xsi:type="archimate:SketchModelActor"
          id="id-95de0b01eb1943e09ccef22e595b4dca"
          name="Direktør Digitalisering, IKT og analyse">
        <bounds
            x="264"
            y="9"
            width="75"
            height="100"/>
      </children>
    </children>
  </children>
</archimate:SketchModel>
